metabeyond/__init__.py
metabeyond/hints.py
metabeyond/remarks/__init__.py
metabeyond/remarks/_intern.py
metabeyond/remarks/impl.py
metabeyond/remarks/introspect.py
metabeyond/remarks/predication.py
metabeyond/typehints/__init__.py
metabeyond/typehints/json.py
metabeyond-0.2.2.dist-info/LICENSE
metabeyond-0.2.2.dist-info/METADATA
metabeyond-0.2.2.dist-info/WHEEL
metabeyond-0.2.2.dist-info/top_level.txt
metabeyond-0.2.2.dist-info/RECORD
